achallonge/__init__.py
achallonge/api.py
achallonge/attachments.py
achallonge/matches.py
achallonge/participants.py
achallonge/tournaments.py
apychal-1.12.0.dist-info/LICENSE
apychal-1.12.0.dist-info/METADATA
apychal-1.12.0.dist-info/WHEEL
apychal-1.12.0.dist-info/top_level.txt
apychal-1.12.0.dist-info/RECORD
