Metadata-Version: 2.1
Name: apychal
Version: 1.12.0
Summary: Async version of pychal (drop-in replacement to pychallonge)
Home-page: https://github.com/Wonderfall/apychal
Author: Wonderfall
Author-email: wonderfall@protonmail.com
License: Public Domain
Keywords: tournaments,challonge
Platform: any
Classifier: Development Status :: 5 - Production/Stable
Classifier: Intended Audience :: Developers
Classifier: License :: Public Domain
Classifier: Operating System :: OS Independent
Classifier: Programming Language :: Python :: 3.6
Classifier: Programming Language :: Python :: 3.7
Classifier: Programming Language :: Python :: 3.8
Classifier: Programming Language :: Python :: 3.9
Classifier: Programming Language :: Python :: 3.10
License-File: LICENSE
Requires-Dist: iso8601
Requires-Dist: tzlocal
Requires-Dist: pytz
Requires-Dist: aiohttp (==3.8.*)
